hopwise/.Dockerfile
hopwise/__init__.py
hopwise/__main__.py
hopwise/cli.py
hopwise/config/__init__.py
hopwise/config/configurator.py
hopwise/data/__init__.py
hopwise/data/interaction.py
hopwise/data/transform.py
hopwise/data/utils.py
hopwise/data/dataloader/__init__.py
hopwise/data/dataloader/abstract_dataloader.py
hopwise/data/dataloader/general_dataloader.py
hopwise/data/dataloader/knowledge_dataloader.py
hopwise/data/dataloader/user_dataloader.py
hopwise/data/dataset/__init__.py
hopwise/data/dataset/customized_dataset.py
hopwise/data/dataset/dataset.py
hopwise/data/dataset/decisiontree_dataset.py
hopwise/data/dataset/kg_dataset.py
hopwise/data/dataset/kg_path_dataset.py
hopwise/data/dataset/kg_seq_dataset.py
hopwise/data/dataset/sequential_dataset.py
hopwise/dataset_example/ml-100k/ml-100k.inter
hopwise/dataset_example/ml-100k/ml-100k.item
hopwise/dataset_example/ml-100k/ml-100k.kg
hopwise/dataset_example/ml-100k/ml-100k.link
hopwise/dataset_example/ml-100k/ml-100k.user
hopwise/evaluator/__init__.py
hopwise/evaluator/base_metric.py
hopwise/evaluator/collector.py
hopwise/evaluator/evaluator.py
hopwise/evaluator/metrics.py
hopwise/evaluator/register.py
hopwise/evaluator/utils.py
hopwise/model/__init__.py
hopwise/model/abstract_recommender.py
hopwise/model/init.py
hopwise/model/layers.py
hopwise/model/logits_processor.py
hopwise/model/loss.py
hopwise/model/sequence_postprocessor.py
hopwise/model/context_aware_recommender/__init__.py
hopwise/model/context_aware_recommender/afm.py
hopwise/model/context_aware_recommender/autoint.py
hopwise/model/context_aware_recommender/dcn.py
hopwise/model/context_aware_recommender/dcnv2.py
hopwise/model/context_aware_recommender/deepfm.py
hopwise/model/context_aware_recommender/dssm.py
hopwise/model/context_aware_recommender/eulernet.py
hopwise/model/context_aware_recommender/ffm.py
hopwise/model/context_aware_recommender/fignn.py
hopwise/model/context_aware_recommender/fm.py
hopwise/model/context_aware_recommender/fnn.py
hopwise-0.9.1.post1.dist-info/METADATA
hopwise-0.9.1.post1.dist-info/WHEEL
hopwise-0.9.1.post1.dist-info/entry_points.txt
hopwise-0.9.1.post1.dist-info/licenses/LICENSE
hopwise-0.9.1.post1.dist-info/RECORD
