Metadata-Version: 2.4
Name: hopwise
Version: 0.9.1.post1
Summary: _hopwise_ is an advanced extension of the Recbole library, designed to enhance recommendation systems with the power of knowledge graphs. By integrating knowledge embedding models, path-based reasoning methods, and path language modeling apporaches, hopwise supports both recommendation and link prediction tasks with a focus on interpretability and self-explanation.
Author-email: Giacomo Medda <jackm.medda@gmail.com>, Ludovico Boratto <ludovico.boratto@acm.org>, Mirko Marras <mirko.marras@acm.org>, Alessandro Soccol <alessandrosoccol@gmail.com>
License: MIT License
License-File: LICENSE
Keywords: explainability,knowledge graph,language models,path modeling,recommender systems
Classifier: Intended Audience :: Developers
Classifier: Intended Audience :: Science/Research
Classifier: Operating System :: OS Independent
Classifier: Programming Language :: Python
Classifier: Programming Language :: Python :: 3 :: Only
Classifier: Programming Language :: Python :: 3.9
Classifier: Programming Language :: Python :: 3.10
Classifier: Programming Language :: Python :: 3.11
Classifier: Programming Language :: Python :: 3.12
Classifier: Topic :: Software Development :: Libraries :: Python Modules
Requires-Python: <3.13,>=3.9
Requires-Dist: cachetools
Requires-Dist: colorama>=0.4.4
Requires-Dist: colorlog>=4.7.2
Requires-Dist: numba>=0.59.0
Requires-Dist: numpy<=1.24.4; python_version < '3.10'
Requires-Dist: numpy>=2.0.0; python_version >= '3.10'
Requires-Dist: pandas<2.0.3,>1.3.0; python_version < '3.10'
Requires-Dist: pandas>2.0.0; python_version >= '3.10'
Requires-Dist: protobuf==3.20.*
Requires-Dist: psutil
Requires-Dist: rich
Requires-Dist: scikit-learn
Requires-Dist: scipy>=1.12.0
Requires-Dist: tabulate
Requires-Dist: tensorboard>=2.5.0
Requires-Dist: texttable
Requires-Dist: thop
Requires-Dist: torch>=2.5.0
Requires-Dist: tqdm
Requires-Dist: wandb
Provides-Extra: all-models
Requires-Dist: accelerate>=0.26.0; extra == 'all-models'
Requires-Dist: datasets; extra == 'all-models'
Requires-Dist: dgl>=2.4.0; extra == 'all-models'
Requires-Dist: faiss-cpu; extra == 'all-models'
Requires-Dist: igraph; extra == 'all-models'
Requires-Dist: joblib; extra == 'all-models'
Requires-Dist: kmeans-pytorch; extra == 'all-models'
Requires-Dist: lightgbm; extra == 'all-models'
Requires-Dist: networkx; extra == 'all-models'
Requires-Dist: python-louvain; extra == 'all-models'
Requires-Dist: transformers; extra == 'all-models'
Requires-Dist: xgboost; extra == 'all-models'
Provides-Extra: cli
Requires-Dist: click>=8.0.0; extra == 'cli'
Provides-Extra: hyper
Requires-Dist: hyperopt==0.2.5; extra == 'hyper'
Requires-Dist: optuna; extra == 'hyper'
Requires-Dist: plotly; extra == 'hyper'
Requires-Dist: ray[tune]; extra == 'hyper'
Provides-Extra: kgat
Requires-Dist: dgl>=2.4.0; extra == 'kgat'
Provides-Extra: ldiffrec
Requires-Dist: kmeans-pytorch; extra == 'ldiffrec'
Provides-Extra: lightgbm
Requires-Dist: lightgbm; extra == 'lightgbm'
Provides-Extra: ncl
Requires-Dist: faiss-cpu; extra == 'ncl'
Provides-Extra: nncf
Requires-Dist: networkx; extra == 'nncf'
Requires-Dist: python-louvain; extra == 'nncf'
Provides-Extra: pathlm
Requires-Dist: accelerate>=0.26.0; extra == 'pathlm'
Requires-Dist: datasets; extra == 'pathlm'
Requires-Dist: igraph; extra == 'pathlm'
Requires-Dist: joblib; extra == 'pathlm'
Requires-Dist: transformers; extra == 'pathlm'
Provides-Extra: tsne
Requires-Dist: opentsne; extra == 'tsne'
Requires-Dist: plotly; extra == 'tsne'
Provides-Extra: xgboost
Requires-Dist: xgboost; extra == 'xgboost'
